pointsim/__init__.py
pointsim/controller.py
pointsim/cython_pid.cp313-win_amd64.pyd
pointsim/simulator2D.py
pointsim/simulator3D.py
pointsim-0.0.1.dist-info/LICENSE
pointsim-0.0.1.dist-info/METADATA
pointsim-0.0.1.dist-info/WHEEL
pointsim-0.0.1.dist-info/top_level.txt
pointsim-0.0.1.dist-info/RECORD
