Metadata-Version: 2.1
Name: pointsim
Version: 0.0.1
Summary: A module for simulating a point and controlling points.
Home-page: https://github.com/OnisOris/pointsim
Author: OnisOris
Author-email: onisoris@yandex.ru
Project-URL: GitHub, https://github.com/OnisOris/pointsim
Keywords: PID control point simulation
Classifier: Programming Language :: Python :: 3.12
Classifier: License :: OSI Approved :: GNU General Public License v2 (GPLv2)
Classifier: Operating System :: OS Independent
Requires-Python: >=3.9
License-File: LICENSE
Requires-Dist: numpy
Requires-Dist: matplotlib
Requires-Dist: PyQt5
